typeytypey/__init__.py
typeytypey/typeytypey.py
typeytypey-0.1.0.dist-info/LICENSE
typeytypey-0.1.0.dist-info/METADATA
typeytypey-0.1.0.dist-info/WHEEL
typeytypey-0.1.0.dist-info/entry_points.txt
typeytypey-0.1.0.dist-info/top_level.txt
typeytypey-0.1.0.dist-info/RECORD
