Metadata-Version: 2.1
Name: typeytypey
Version: 0.1.0
Summary: A Linux CLI demo replay tool, written in Python 3
Home-page: https://github.com/mrda/typeytypey
Author: Michael Davies
Author-email: michael@the-davies.net
License: UNKNOWN
Platform: UNKNOWN
Classifier: Programming Language :: Python :: 3
Classifier: License :: OSI Approved :: GNU General Public License v3 or later (GPLv3+)
Classifier: Operating System :: OS Independent
